ritetag/__init__.py
ritetag/__version__.py
ritetag/api.py
ritetag/builders.py
ritetag/console.py
ritetag/decorators.py
ritetag/enums.py
ritetag/exceptions.py
ritetag/others.py
ritetag/response.py
ritetag-1.3.3.data/scripts/ritetag-api
ritetag-1.3.3.dist-info/LICENCE
ritetag-1.3.3.dist-info/METADATA
ritetag-1.3.3.dist-info/WHEEL
ritetag-1.3.3.dist-info/top_level.txt
ritetag-1.3.3.dist-info/RECORD
