Metadata-Version: 2.1
Name: ritetag
Version: 1.3.3
Summary: RiteTag API client.
Home-page: https://github.com/pavelhouzva/ritetag-api-python
Author: Pavel HouÅ¾va
Author-email: pavel@ritekit.com
Classifier: License :: OSI Approved :: Apache Software License
Classifier: Operating System :: OS Independent
Classifier: Programming Language :: Python
Classifier: Programming Language :: Python :: 2.7
Classifier: Programming Language :: Python :: 3
Classifier: Programming Language :: Python :: 3.5
Classifier: Programming Language :: Python :: 3.6
Classifier: Programming Language :: Python :: 3.7
Classifier: Programming Language :: Python :: 3.8
Classifier: Programming Language :: Python :: 3.9
Requires: requests
Requires-Python: >=2.7
License-File: LICENCE
